Metadata-Version: 2.1
Name: pyshell-pybc2-updated
Version: 0.0.1
Summary: This Package contains the commands of UNIX shell
Home-page: UNKNOWN
Author: PYBC_2
Author-email: lakshmip@adobe.com
License: UNKNOWN
Platform: UNKNOWN
Classifier: Programming Language :: Python :: 3
Classifier: Operating System :: OS Independent
